weathercache/__init__.py
weathercache/api.py
weathercache/config_management.py
weathercache/rac5.py
weathercache/rac5_daily.py
weathercache/rac5_hourly.py
weathercache/version.py
weathercache-0.0.1.dist-info/licenses/AUTHORS.rst
weathercache-0.0.1.dist-info/licenses/LICENSE
weathercache-0.0.1.dist-info/METADATA
weathercache-0.0.1.dist-info/WHEEL
weathercache-0.0.1.dist-info/top_level.txt
weathercache-0.0.1.dist-info/RECORD
